ngflask/__init__.py
ngflask/flask_ngrok.py
ngflask-1.0.5.dist-info/LICENSE
ngflask-1.0.5.dist-info/METADATA
ngflask-1.0.5.dist-info/WHEEL
ngflask-1.0.5.dist-info/entry_points.txt
ngflask-1.0.5.dist-info/top_level.txt
ngflask-1.0.5.dist-info/RECORD
