Metadata-Version: 2.1
Name: ngflask
Version: 1.0.5
Summary: File-sharing tool
Home-page: https://github.com/cyberhexe/ngflask
Author: totekuh
Author-email: totekuh@protonmail.com
License: UNKNOWN
Project-URL: Bug Reports, https://github.com/cyberhexe/ngflask/issues
Project-URL: Source, https://github.com/cyberhexe/ngflask
Keywords: file-sharing,ngrok,flask
Platform: UNKNOWN
Classifier: Development Status :: 5 - Production/Stable
Classifier: Environment :: Console
Classifier: Intended Audience :: Information Technology
Classifier: Intended Audience :: Other Audience
Classifier: License :: OSI Approved :: MIT License
Classifier: Operating System :: POSIX :: Linux
Classifier: Operating System :: Microsoft :: Windows
Classifier: Programming Language :: Python :: 3
Classifier: Programming Language :: Python :: 3.6
Classifier: Programming Language :: Python :: 3.7
Classifier: Programming Language :: Python :: 3.8
Classifier: Programming Language :: Python :: 3.9
Classifier: Programming Language :: Python :: 3 :: Only
Requires-Python: >=3.6, <4
License-File: LICENSE
Requires-Dist: flask
Requires-Dist: flask-autoindex
Requires-Dist: pyngrok
